wordcookies/__init__.py
wordcookies/__main__.py
wordcookies/cli.py
wordcookies/game.py
wordcookies/generator.py
wordcookies-1.0.1.dist-info/LICENSE
wordcookies-1.0.1.dist-info/METADATA
wordcookies-1.0.1.dist-info/WHEEL
wordcookies-1.0.1.dist-info/entry_points.txt
wordcookies-1.0.1.dist-info/top_level.txt
wordcookies-1.0.1.dist-info/RECORD
