Metadata-Version: 2.1
Name: wordcookies
Version: 1.0.1
Summary: Word Cookies helper/solver/answers
Home-page: https://github.com/jojoee/wordcookies
Author: Nathachai Thongniran
Author-email: inid3a@gmail.com
License: MIT
Keywords: word,word-cookies,dictionary
Platform: UNKNOWN
Classifier: License :: OSI Approved :: MIT License
Classifier: Operating System :: OS Independent
Classifier: Programming Language :: Python :: 3
Classifier: Programming Language :: Python :: 3.7
Requires-Dist: nltk (==3.5)
Requires-Dist: requests (==2.24.0)
